setup.py
bin/wave
waveradio/__init__.py
waveradio/app.py
waveradio/conf.py
waveradio/main.py
waveradio_0.3.egg-info/PKG-INFO
waveradio_0.3.egg-info/SOURCES.txt
waveradio_0.3.egg-info/dependency_links.txt
waveradio_0.3.egg-info/not-zip-safe
waveradio_0.3.egg-info/requires.txt
waveradio_0.3.egg-info/top_level.txt