Metadata-Version: 2.1
Name: waveradio-0.3
Version: 0.0.1
Summary: serius ini deskripsi
Home-page: UNKNOWN
Author: Muhammad Al Fajri
Author-email: fajrim228@gmail.com
License: unlicensed
Platform: UNKNOWN
